rer.ufficiostampa-3.0.4-py3.10-nspkg.pth
rer/ufficiostampa/__init__.py
rer/ufficiostampa/configure.zcml
rer/ufficiostampa/content.py
rer/ufficiostampa/indexer.py
rer/ufficiostampa/permissions.zcml
rer/ufficiostampa/query_index_modifiers.py
rer/ufficiostampa/setuphandlers.py
rer/ufficiostampa/testing.py
rer/ufficiostampa/upgrades.py
rer/ufficiostampa/upgrades.zcml
rer/ufficiostampa/utils.py
rer/ufficiostampa/adapters/__init__.py
rer/ufficiostampa/adapters/configure.zcml
rer/ufficiostampa/adapters/types.py
rer/ufficiostampa/behaviors/__init__.py
rer/ufficiostampa/behaviors/configure.zcml
rer/ufficiostampa/behaviors/legislature.py
rer/ufficiostampa/behaviors/metadata.py
rer/ufficiostampa/browser/__init__.py
rer/ufficiostampa/browser/configure.zcml
rer/ufficiostampa/browser/controlpanel.py
rer/ufficiostampa/browser/send_mail_helpers.py
rer/ufficiostampa/browser/show_send_links.py
rer/ufficiostampa/browser/static/logo_rer.gif
rer/ufficiostampa/browser/templates/cancel_subscriptions_mail_template.pt
rer/ufficiostampa/browser/templates/cancel_subscriptions_notify_template.pt
rer/ufficiostampa/browser/templates/controlpanel_layout.pt
rer/ufficiostampa/browser/templates/send_mail_template.pt
rer/ufficiostampa/browser/templates/send_preview.pt
rer/ufficiostampa/events/__init__.py
rer/ufficiostampa/events/comunicato.py
rer/ufficiostampa/events/configure.zcml
rer/ufficiostampa/interfaces/__init__.py
rer/ufficiostampa/interfaces/content.py
rer/ufficiostampa/interfaces/layer.py
rer/ufficiostampa/interfaces/settings.py
rer/ufficiostampa/interfaces/store.py
rer/ufficiostampa/locales/README.rst
rer/ufficiostampa/locales/__init__.py
rer/ufficiostampa/locales/manual.pot
rer/ufficiostampa/locales/rer.ufficiostampa.pot
rer/ufficiostampa/locales/update.py
rer/ufficiostampa/locales/update.sh
rer/ufficiostampa/locales/it/LC_MESSAGES/plone.mo
rer/ufficiostampa/locales/it/LC_MESSAGES/plone.po
rer/ufficiostampa/locales/it/LC_MESSAGES/rer.ufficiostampa.mo
rer.ufficiostampa-3.0.4.dist-info/LICENSE.GPL
rer.ufficiostampa-3.0.4.dist-info/LICENSE.rst
rer.ufficiostampa-3.0.4.dist-info/METADATA
rer.ufficiostampa-3.0.4.dist-info/WHEEL
rer.ufficiostampa-3.0.4.dist-info/entry_points.txt
rer.ufficiostampa-3.0.4.dist-info/namespace_packages.txt
rer.ufficiostampa-3.0.4.dist-info/top_level.txt
rer.ufficiostampa-3.0.4.dist-info/RECORD
