Metadata-Version: 2.1
Name: rer.ufficiostampa
Version: 3.0.4
Summary: Policy for Ufficio Stampa
Home-page: https://github.com/RegioneER/rer.ufficiostampa
Author: RedTurtle Technology
Author-email: sviluppo@redturtle.it
License: GPL version 2
Project-URL: PyPI, https://pypi.python.org/pypi/rer.ufficiostampa
Project-URL: Source, https://github.com/RegioneER/rer.ufficiostampa
Project-URL: Tracker, https://github.com/RegioneER/rer.ufficiostampa/issues
Keywords: Python Plone
Classifier: Development Status :: 5 - Production/Stable
Classifier: Environment :: Web Environment
Classifier: Framework :: Plone
Classifier: Framework :: Plone :: Addon
Classifier: Framework :: Plone :: 6.0
Classifier: Programming Language :: Python
Classifier: Programming Language :: Python :: 3.8
Classifier: Programming Language :: Python :: 3.9
Classifier: Programming Language :: Python :: 3.10
Classifier: Programming Language :: Python :: 3.11
Classifier: Operating System :: OS Independent
Classifier: License :: OSI Approved :: GNU General Public License v2 (GPLv2)
Requires-Python: >=3.8
License-File: LICENSE.GPL
License-File: LICENSE.rst
Requires-Dist: setuptools
Requires-Dist: itsdangerous >=1.1.0
Requires-Dist: plone.base
Requires-Dist: premailer
Requires-Dist: requests
Requires-Dist: souper.plone
Requires-Dist: defusedcsv
Requires-Dist: rer.blocks2html
Requires-Dist: collective.volto.blocksfield
Provides-Extra: test
Requires-Dist: plone.app.testing ; extra == 'test'
Requires-Dist: plone.testing >=5.0.0 ; extra == 'test'
Requires-Dist: plone.app.contenttypes ; extra == 'test'
Requires-Dist: plone.app.iterate ; extra == 'test'
Requires-Dist: plone.app.robotframework ; extra == 'test'
Requires-Dist: collective.MockMailHost ; extra == 'test'
